ts2py/__init__.py
ts2py/assets/ts2py.ebnf
ts2py/assets/ts2pyParser.ini
ts2py/main.py
ts2py/syntax/__init__.py
ts2py/syntax/ast.py
ts2py/syntax/compiler.py
ts2py/syntax/parser.py
ts2py/syntax/preprocessor.py
ts2py/types/__init__.py
ts2py/types/args.py
ts2py/types/dhparser.py
ts2py/utils/__init__.py
ts2py/utils/config.py
ts2py/utils/helper.py
ts2py/utils/logger.py
ts2py-0.0.2.dist-info/WHEEL
ts2py-0.0.2.dist-info/LICENSE
ts2py-0.0.2.dist-info/METADATA
ts2py-0.0.2.dist-info/entry_points.txt
ts2py-0.0.2.dist-info/RECORD
