Metadata-Version: 2.1
Name: ts2py
Version: 0.0.2
Summary: Python-Interoperability for Typescript-Interfaces
Home-page: https://github.com/thelicato/ts2py
License: Apache-2.0
Keywords: Typescript to Python converter,Typescript Interface,Python TypedDict
Author: Angelo Delicato
Author-email: thelicato@duck.com
Requires-Python: >=3.10,<4.0
Classifier: Development Status :: 3 - Alpha
Classifier: Environment :: Console
Classifier: Intended Audience :: Developers
Classifier: License :: OSI Approved :: Apache Software License
Classifier: Operating System :: OS Independent
Classifier: Programming Language :: Python :: 3
Classifier: Programming Language :: Python :: 3.10
Classifier: Programming Language :: Python :: 3.11
Classifier: Programming Language :: Python :: 3
Classifier: Programming Language :: Python :: 3.10
Classifier: Programming Language :: Python :: 3.11
Classifier: Programming Language :: Python :: Implementation :: CPython
Classifier: Programming Language :: Python :: Implementation :: PyPy
Classifier: Topic :: Software Development :: Code Generators
Classifier: Topic :: Software Development :: Compilers
Classifier: Topic :: Text Processing :: Markup
Requires-Dist: dhparser (>=1.3.3,<2.0.0)
Requires-Dist: typer[all] (>=0.7.0,<0.8.0)
Requires-Dist: typing-extensions (>=4.4.0,<5.0.0)
Project-URL: Repository, https://github.com/thelicato/ts2py
